{
  "area_condition": {
    "type": "neighbor_based_generation",
    "must_have": {
      "block": "minecraft:air",
      "predicate_type": "minecraft:block_match"
    }
  },
  "growth_chance": 0.05,
  "growth_for_face": [
    {
      "direction": "up",
      "growth": [
        {
          "data": {
            "block": {
              "Name": "immersive_weathering:frosty_grass",
              "Properties": {
                "natural": "true"
              }
            }
          },
          "weight": 1
        }
      ],
      "weight": 1
    }
  ],
  "owners": "minecraft:short_grass",
  "position_predicates": [
    {
      "type": "biome_match",
      "biomes": "#immersive_weathering:icy"
    },
    {
      "type": "day_test",
      "day": false
    }
  ],
  "replacing_target": {
    "block": "minecraft:air",
    "predicate_type": "minecraft:block_match"
  },
  "target_self": true,
  "tick_sources": [
    "block_tick"
  ]
}